versioned_fastapi/__init__.py
versioned_fastapi/version_fastapi.py
versioned_fastapi-1.0.2.dist-info/METADATA
versioned_fastapi-1.0.2.dist-info/WHEEL
versioned_fastapi-1.0.2.dist-info/licenses/LICENSE
versioned_fastapi-1.0.2.dist-info/RECORD
