Metadata-Version: 2.3
Name: versioned-fastapi
Version: 1.0.2
Summary: Simple versioning of FastAPI web applications
Project-URL: Documentation, https://github.com/mivoelcker/versioned-fastapi#readme
Project-URL: Source, https://github.com/mivoelcker/versioned-fastapi
License-Expression: MIT
License-File: LICENSE
Keywords: fastapi,version,versioned-fastapi,versioning
Classifier: Programming Language :: Python
Classifier: Programming Language :: Python :: 3
Classifier: Programming Language :: Python :: 3.8
Classifier: Programming Language :: Python :: 3.9
Classifier: Programming Language :: Python :: 3.10
Classifier: Programming Language :: Python :: 3.11
Classifier: Programming Language :: Python :: 3.12
Requires-Python: >=3.8
Requires-Dist: fastapi>=0.88.0
